matilda/__init__.py
matilda/main_matilda_rna_task.py
matilda/main_matilda_rna_train.py
matilda/main_matilda_task.py
matilda/main_matilda_train.py
matilda/util.py
matilda/learn/__init__.py
matilda/learn/model.py
matilda/learn/model_rna.py
matilda/learn/predict.py
matilda/learn/train.py
matilda_sc-0.1.dist-info/METADATA
matilda_sc-0.1.dist-info/WHEEL
matilda_sc-0.1.dist-info/licenses/LICENSE
matilda_sc-0.1.dist-info/RECORD
