Metadata-Version: 2.1
Name: Matilda_sc
Version: 0.1
Summary: A multi-modal single cell sequencing analysis tool
Project-URL: Homepage, https://github.com/PYangLab/Matilda/tree/main
Project-URL: Issues, https://github.com/PYangLab/Matilda/tree/main/issues
Author-email: Chunlei Liu <chunlei@cmri.com>
License-File: LICENSE
Classifier: License :: OSI Approved :: MIT License
Classifier: Operating System :: OS Independent
Classifier: Programming Language :: Python :: 3
Requires-Python: >=3.0
